solartotr/__init__.py
solartotr/solartotr.py
solartotr-0.0.2.dist-info/LICENSE
solartotr-0.0.2.dist-info/METADATA
solartotr-0.0.2.dist-info/WHEEL
solartotr-0.0.2.dist-info/top_level.txt
solartotr-0.0.2.dist-info/RECORD
