Metadata-Version: 2.1
Name: solartotr
Version: 0.0.2
Summary: Convert a solar gain on human to radiant temperature.
Home-page: https://github.com/zhushaohz/SolartoTr
Author: zhushaohz
Author-email: zhushaohz@gmail.com
License: UNKNOWN
Project-URL: Bug Tracker, https://github.com/zhushaohz/SolartoTr/issues
Platform: UNKNOWN
Classifier: Development Status :: 3 - Alpha
Classifier: Intended Audience :: Education
Classifier: Intended Audience :: Science/Research
Classifier: License :: OSI Approved :: MIT License
Classifier: Operating System :: OS Independent
Classifier: Programming Language :: Python :: 3
Classifier: Programming Language :: Python :: 3.6
Classifier: Programming Language :: Python :: 3.7
Classifier: Programming Language :: Python :: 3.8
Classifier: Topic :: Software Development :: Libraries :: Python Modules
Classifier: Topic :: Utilities
Requires-Python: >=3.6
License-File: LICENSE
